mocap_cpp_operations/__init__.py
mocap_cpp_operations/axengine_1728989291_3668890942.py
mocap_cpp_operations/operations/__init__.py
mocap_cpp_operations/operations/opsMocap.py
mocap_cpp_operations/operations/opsTrackingCalib.py
mocap_cpp_operations/tracking/__init__.py
mocap_cpp_operations/tracking/box_tracking.py
mocap_cpp_operations/tracking/box_tracklet_util.py
mocap_cpp_operations/tracking/calib_tracking.py
mocap_cpp_operations/tracking/common_tracking.py
mocap_cpp_operations/tracking/deep_sort/__init__.py
mocap_cpp_operations/tracking/deep_sort/deep/__init__.py
mocap_cpp_operations/tracking/deep_sort/deep/evaluate.py
mocap_cpp_operations/tracking/deep_sort/deep/feature_extractor.py
mocap_cpp_operations/tracking/deep_sort/deep/model.py
mocap_cpp_operations/tracking/deep_sort/deep/original_model.py
mocap_cpp_operations/tracking/deep_sort/deep/test.py
mocap_cpp_operations/tracking/deep_sort/deep/train.jpg
mocap_cpp_operations/tracking/deep_sort/deep/train.py
mocap_cpp_operations/tracking/deep_sort/deep_sort.py
mocap_cpp_operations/tracking/deep_sort/sort/__init__.py
mocap_cpp_operations/tracking/deep_sort/sort/detection.py
mocap_cpp_operations/tracking/deep_sort/sort/iou_matching.py
mocap_cpp_operations/tracking/deep_sort/sort/kalman_filter.py
mocap_cpp_operations/tracking/deep_sort/sort/linear_assignment.py
mocap_cpp_operations/tracking/deep_sort/sort/nn_matching.py
mocap_cpp_operations/tracking/deep_sort/sort/preprocessing.py
mocap_cpp_operations/tracking/deep_sort/sort/track.py
mocap_cpp_operations/tracking/deep_sort/sort/tracker.py
mocap_cpp_operations/tracking/dst_metrics_stats.py
mocap_cpp_operations/tracking/feature_extraction.py
mocap_cpp_operations/tracking/k_way_matching.py
mocap_cpp_operations/tracking/matching_mv_temporal.py
mocap_cpp_operations/tracking/min_cost_flow_mv_tracking.py
mocap_cpp_operations/tracking/mocap_data_parse.py
mocap_cpp_operations/tracking/multi_stage_mv_tracking.py
mocap_cpp_operations/tracking/pose_2d_tracking.py
mocap_cpp_operations-2.3.3.dist-info/METADATA
mocap_cpp_operations-2.3.3.dist-info/WHEEL
mocap_cpp_operations-2.3.3.dist-info/RECORD
