Metadata-Version: 2.1
Name: mocap-cpp-operations
Version: 2.3.3
Summary: 
Keywords: MotionOps,Moveai
Author: move.ai
Author-email: info@move.ai
Requires-Python: >=3.10,<4.0
Classifier: Programming Language :: Python :: 3
Classifier: Programming Language :: Python :: 3.10
Classifier: Programming Language :: Python :: 3.11
Classifier: Programming Language :: Python :: 3.12
Requires-Dist: avro (>=1.11.2,<2.0.0)
Requires-Dist: filterpy (>=1.4.5,<2.0.0)
Requires-Dist: mocap-base (>=2.0.1,<3.0.0)
Requires-Dist: mocap-calibration (>=2.4.0,<3.0.0)
Requires-Dist: mocap_settings (>=1.4.9,<2.0.0)
Requires-Dist: networkx (>=3.1,<4.0)
Requires-Dist: numba (>=0.60.0,<0.61.0)
Requires-Dist: pandas (>=2.1.1,<3.0.0)
Requires-Dist: torch (==1.13.0)
Requires-Dist: torchreid (>=0.2.5,<0.3.0)
Requires-Dist: torchvision (==0.14.0)
Requires-Dist: tqdm (>=4.66.1,<5.0.0)
